py_kor/__init__.py
py_kor/pk_design_patterns/__init__.py
py_kor/pk_design_patterns/implementation/__init__.py
py_kor/pk_design_patterns/implementation/singleton.py
py_kor/pk_mixins/__init__.py
py_kor/pk_mixins/implementation/__init__.py
py_kor/pk_mixins/implementation/choice_enum.py
py_kor/pk_mixins/implementation/generics.py
py_kor/pk_types/__init__.py
py_kor/pk_types/implementation/__init__.py
py_kor/pk_types/implementation/mutable.py
py_kor/pk_utilities/__init__.py
py_kor/pk_utilities/implementation/__init__.py
py_kor/pk_utilities/implementation/path_dict.py
py_kor/pk_utilities/implementation/scope.py
py_kor/pk_utilities/implementation/utilities/__init__.py
py_kor/pk_utilities/implementation/utilities/function_helpers.py
tests/__init__.py
tests/pk_design_patterns/__init__.py
tests/pk_design_patterns/test_singleton.py
tests/pk_mixins/__init__.py
tests/pk_mixins/test_choice_enum.py
tests/pk_types/__init__.py
tests/pk_types/test_mutable.py
tests/pk_utilities/__init__.py
tests/pk_utilities/test_scope.py
py_kor-0.0.5.dist-info/LICENSE
py_kor-0.0.5.dist-info/METADATA
py_kor-0.0.5.dist-info/WHEEL
py_kor-0.0.5.dist-info/top_level.txt
py_kor-0.0.5.dist-info/RECORD
